{"expireTime":9007200871728444000,"key":"transformer-remark-markdown-html-ast-bf9e388f1729db80f83923deee6f109d--","val":{"type":"root","children":[{"type":"element","tagName":"p","properties":{},"children":[{"type":"text","value":"About this Event\nHungry for new collaborators? Looking to expand your community? Want to connect with like-minded queer theatre workers?\nJoin us for a Valentine's Day Mash-Up of three orgs! Ring of Keys, MeetCute and SORORITY are joining forces for a night of meeting old friends, new collaborators, and all in between! Join us for an evening of virtual artistic speed dating, community expanding and so much more.\nFacilitator Bios:\nMeetCute (founded and run by Los Angeles directors Katie Lindsay and Hannah Wolf) is a community building organization rooted in inclusive practices, partnering artists and serving the Los Angeles theatre community. Learn more at ","position":{"start":{"line":1,"column":1,"offset":0},"end":{"line":5,"column":231,"offset":663}}},{"type":"element","tagName":"a","properties":{"href":"https://www.meetcute-la.com/"},"children":[{"type":"text","value":"https://www.meetcute-la.com/","position":{"start":{"line":5,"column":231,"offset":663},"end":{"line":5,"column":259,"offset":691}}}],"position":{"start":{"line":5,"column":231,"offset":663},"end":{"line":5,"column":259,"offset":691}}},{"type":"text","value":"\nSORORITY started as a late night k-hole for new short works by women, trans and queer performing artists working in Los Angeles. Founded, curated and hosted by Gina Young, SORORITY exploded almost overnight from a small salon into a huge and supportive community of creators with a cult following. SORORITY events defy description and spark conversation, and we've produced hundreds of artists at venues including The Hammer Museum, Rockwell, and Los Angeles Performance Practice's LAX Festival. During this time of COVID-19 and social distancing, SORORITY is now on Zoom and YouTube. www.sororitytheaterprojects.com\nInstagram- @meet.cute.la and Facebook\nSORORITY- @sororitytheatre","position":{"start":{"line":5,"column":259,"offset":691},"end":{"line":8,"column":27,"offset":1373}}}],"position":{"start":{"line":1,"column":1,"offset":0},"end":{"line":8,"column":27,"offset":1373}}}],"position":{"start":{"line":1,"column":1,"offset":0},"end":{"line":8,"column":27,"offset":1373}}}}