{"data":{"datoCmsKey":{"name":"Kai Alexander Judd","id":"DatoCmsKey-4573960-en","pronouns":"He / they","headshot":{"url":"https://www.datocms-assets.com/20110/1587436426-kaij31.jpg","title":"4573960 via Editor1587436436799"},"featuredImage":{"url":"https://www.datocms-assets.com/20110/1587436359-kai-alexander-judd-headshot-3.jpg","alt":"editor-uploaded image"},"email":"kaialexanderjudd@gmail.com","website":"https://kaialexanderjudd.com","memberSince":"","socialMedia":[{"socialMediaLink":"https://instagram.com/artfulkai"},{"socialMediaLink":"https://facebook.com/artfulkai"}],"genderIdentity":"Transmasculine","sexualIdentity":"Queer / pansexual","raceEthnicity":"","mainLocation":"New York City","locations":"Minneapolis / St. Paul| New York City| San Francisco / Oakland","affiliations":"AEA","vocalRange":"Tenor","danceExperience":"","discipline":"Actor","bio":"Trans, hapa actor, set to graduate with a BFA in Music Theatre from Viterbo University May 2020. CA grown, NY bound!\nI want to put my heart and soul into tales of intersectional liberation onstage. I also wanna take the existing canon and bring new depth to familiar characters. Mostly just looking to collaborate with folx of all kinds, run around, and sing.","resume":"https://static1.squarespace.com/static/5de178aef5155d068a3c5ff2/t/5e62897eaa554604ce3a0529/1583516071578/Kai+Alexander+Judd+-+Resume.pdf"}},"pageContext":{"slug":"kai-alexander-judd"}}