{"data":{"datoCmsKey":{"name":"Emmett Grosland","id":"DatoCmsKey-4649768-en","pronouns":"They or He","headshot":{"url":"https://www.datocms-assets.com/20110/1584892112-rokfavicon.png","title":"TestUser with'Apostrophe 1584892114178"},"featuredImage":null,"email":"emgrosland@gmail.com","website":"https://Www.emgrosland.com","memberSince":"2020","socialMedia":[],"genderIdentity":"Non-binary trans guy","sexualIdentity":"Whatever","raceEthnicity":"","mainLocation":"New York (have Chicago housing)","locations":"","affiliations":"AEA, SAG/AFTRA","vocalRange":"Tenor alto","danceExperience":"Former dancer, current mover","discipline":"Actor, scenic artist","bio":"","resume":""}},"pageContext":{"slug":"emmett-grosland"}}