{"data":{"datoCmsKey":{"name":"Hannah Lang","id":"DatoCmsKey-2833440-en","pronouns":"she / they","headshot":{"url":"https://www.datocms-assets.com/20110/1581659199-lang.jpg","title":null},"featuredImage":null,"email":"hannahelizabethlang@gmail.com","website":"","memberSince":"2019","socialMedia":[{"socialMediaLink":"https://instagram.com/hnnh.lng"},{"socialMediaLink":"https://www.linkedin.com/in/hannah-lang-4279a9104/"}],"genderIdentity":"who knows, tbh","sexualIdentity":"queer","raceEthnicity":"","mainLocation":"NYC","locations":"NYC","affiliations":"","vocalRange":"","danceExperience":"","discipline":"Producer, Director, Choreographer, Artistic Director","bio":"Hannah Lang is a Chicago-born queer producer and theatre-maker living in Brooklyn. She is the proud founder of Three of Cups Theatre Collective, and currently works at BAM as an Artist Services Representative. They have previously worked as the Producing Artistic Associate at New York Musical Festival and an Artistic Associate at Hypokrit Theatre Company. Hannah is also a historian, having earned their M.A. in History from St. John's University, concentrating primarily on LGBTQ+ history and gender non-conformity in 20th-century America. She is most passionate about producing work that uplifts queer/trans voices and builds community.  ","resume":""}},"pageContext":{"slug":"hannah-lang"}}