{"data":{"datoCmsKey":{"name":"James T. Washburn","id":"DatoCmsKey-2837932-en","pronouns":"He / Him / His","headshot":{"url":"https://www.datocms-assets.com/20110/1581704490-screen-shot-2020-02-14-at-1-21-27-pm.png","title":null},"featuredImage":{"url":"https://www.datocms-assets.com/20110/1600495557-nowhere-7870.jpg","alt":"editor-uploaded image of James T. Washburn"},"email":"jamestheodorew@gmail.com","website":"https://www.jamestwashburn.com","memberSince":"2019","socialMedia":[{"socialMediaLink":"https://www.instagram.com/starry_eyed_boy"},{"socialMediaLink":"https://www.facebook.com/jamestwashburnplaywright"},{"socialMediaLink":"https://www.youtube.com/channel/UCVH2i2en65ItAe8l18hxHTQ"},{"socialMediaLink":"https://www.linkedin.com/in/james-washburn-03284a13a/"}],"genderIdentity":"Trans masculine","sexualIdentity":"Gay","raceEthnicity":"","mainLocation":"Seattle","locations":"Seattle","affiliations":"","vocalRange":"Baritenor","danceExperience":"","discipline":"Writer / Director / Lyricist / Actor","bio":"I am a Seattle-based trans storyteller-activist. \n​\nMy artistic mission:\nTo empower members of the queer community by reclaiming the classics, queering the canon, and using familiar stories and mediums to start difficult conversations.","resume":""}},"pageContext":{"slug":"james-washburn"}}