{"data":{"datoCmsKey":{"name":"Kristin Feeney","id":"DatoCmsKey-2831094-en","pronouns":"She / Her","headshot":{"url":"https://www.datocms-assets.com/20110/1581617134-k-feeney.jpg","title":null},"featuredImage":null,"email":"kristin_feeney@hotmail.com","website":"http://www.kristinfeeney.com/","memberSince":"2018","socialMedia":[],"genderIdentity":"Female","sexualIdentity":"Gay","raceEthnicity":"","mainLocation":"NYC","locations":"NYC","affiliations":"","vocalRange":"","danceExperience":"","discipline":"Actor / Singer","bio":"","resume":""}},"pageContext":{"slug":"kristin-feeney"}}